mlflow_txtai/__init__.py
mlflow_txtai/tracing.py
mlflow_txtai-0.4.0.dist-info/LICENSE
mlflow_txtai-0.4.0.dist-info/METADATA
mlflow_txtai-0.4.0.dist-info/WHEEL
mlflow_txtai-0.4.0.dist-info/top_level.txt
mlflow_txtai-0.4.0.dist-info/RECORD
