Metadata-Version: 2.1
Name: mlflow-txtai
Version: 0.4.0
Summary: MLflow automatic tracing for txtai
Home-page: https://github.com/neuml/mlflow-txtai
Author: NeuML
License: Apache 2.0: http://www.apache.org/licenses/LICENSE-2.0
Project-URL: Documentation, https://github.com/neuml/mlflow-txtai
Project-URL: Issue Tracker, https://github.com/neuml/mlflow-txtai/issues
Project-URL: Source Code, https://github.com/neuml/mlflow-txtai
Keywords: search embedding machine-learning nlp
Classifier: License :: OSI Approved :: Apache Software License
Classifier: Operating System :: OS Independent
Classifier: Programming Language :: Python :: 3
Classifier: Topic :: Scientific/Engineering :: Artificial Intelligence
Classifier: Topic :: Software Development
Classifier: Topic :: Text Processing :: Indexing
Classifier: Topic :: Utilities
Requires-Python: >=3.10
License-File: LICENSE
Requires-Dist: mlflow >=3.1.0
Requires-Dist: txtai >=8.5.0
